add_dashboard_column/__init__.py
add_dashboard_column/extension.py
reviewboard_add_dashboard_column-1.0.5.dist-info/METADATA
reviewboard_add_dashboard_column-1.0.5.dist-info/WHEEL
reviewboard_add_dashboard_column-1.0.5.dist-info/entry_points.txt
reviewboard_add_dashboard_column-1.0.5.dist-info/top_level.txt
reviewboard_add_dashboard_column-1.0.5.dist-info/RECORD
