Metadata-Version: 2.4
Name: reviewboard-add_dashboard_column
Version: 1.0.5
Summary: 为reviewboard添加自定义的列
Author: sijinhui
Author-email: sijinhui <sijinhui@qq.com>
License-Expression: MIT
Project-URL: Homepage, https://github.com/sijinhui/reviewboard-add_dashboard_column
Classifier: Programming Language :: Python :: 3
Classifier: Operating System :: OS Independent
Requires-Python: >=3.9
Dynamic: author
